ratehawk/__init__.py
ratehawk/exceptions.py
ratehawk/limiter.py
ratehawk/algorithms/__init__.py
ratehawk/algorithms/leaky_bucket.py
ratehawk/algorithms/token_bucket.py
ratehawk/monitoring/__init__.py
ratehawk/monitoring/events.py
ratehawk/monitoring/logging.py
ratehawk/monitoring/metrics.py
ratehawk/storage/__init__.py
ratehawk/storage/base.py
ratehawk/storage/memory.py
ratehawk/storage/postgres.py
ratehawk/storage/redis.py
ratehawk/storage/sqlite.py
ratehawk-0.2.1.dist-info/METADATA
ratehawk-0.2.1.dist-info/WHEEL
ratehawk-0.2.1.dist-info/top_level.txt
ratehawk-0.2.1.dist-info/RECORD
