Metadata-Version: 2.1
Name: ratehawk
Version: 0.2.1
Summary: A flexible API rate limiting library for Python
Home-page: https://github.com/wadedesign/ratehawk
Author: Andrew Wade
Author-email: hi@wadedev.online
Classifier: Development Status :: 4 - Beta
Classifier: Intended Audience :: Developers
Classifier: License :: OSI Approved :: MIT License
Classifier: Programming Language :: Python :: 3
Classifier: Programming Language :: Python :: 3.7
Classifier: Programming Language :: Python :: 3.8
Classifier: Programming Language :: Python :: 3.9
Requires-Python: >=3.7
Requires-Dist: redis >=4.0.0
Requires-Dist: aiosqlite >=0.17.0
Requires-Dist: asyncpg >=0.27.0
Requires-Dist: prometheus-client >=0.12.0
Requires-Dist: python-dotenv >=0.19.0
Provides-Extra: dev
Requires-Dist: pytest >=6.0.0 ; extra == 'dev'
Requires-Dist: pytest-asyncio >=0.14.0 ; extra == 'dev'
Requires-Dist: black >=20.8b1 ; extra == 'dev'
Requires-Dist: isort >=5.6.4 ; extra == 'dev'
Provides-Extra: monitoring
Requires-Dist: prometheus-client >=0.12.0 ; extra == 'monitoring'
Requires-Dist: grafana-api-client >=0.3.4 ; extra == 'monitoring'
Requires-Dist: python-dateutil >=2.8.2 ; extra == 'monitoring'
